ezst/__init__.py
ezst/data.py
ezst/test.py
ezst/ai/__init__.py
ezst/ai/art.py
ezst/ai/cnn.py
ezst/ai/disney.py
ezst/ai/dnn.py
ezst/ai/face.py
ezst/ai/image_classifier.py
ezst/ai/model.py
ezst/ai/nlp.py
ezst/colab/__init__.py
ezst/colab/image.py
ezst/cv/__init__.py
ezst/data/__init__.py
ezst/data/art.py
ezst/data/art_data.py
ezst/data/cats_dogs.py
ezst/data/image_samples.py
ezst/data/nahon.py
ezst/data/rps.py
ezst/data/test.py
ezst/util/__init__.py
ezst-0.3.44.dist-info/METADATA
ezst-0.3.44.dist-info/WHEEL
ezst-0.3.44.dist-info/top_level.txt
ezst-0.3.44.dist-info/RECORD
