Metadata-Version: 2.1
Name: ezst
Version: 0.3.44
Summary: ai library for education
Home-page: https://github.com/ezstkr/pypi_ezst
Author: aiacademy
Author-email: aiacademy131@gamil.com
License: UNKNOWN
Download-URL: https://github.com/ezstkr/pypi_ezst/archive/master.zip
Keywords: pypi deploy
Platform: UNKNOWN
Classifier: Programming Language :: Python :: 3
Classifier: Programming Language :: Python :: 3.2
Classifier: Programming Language :: Python :: 3.3
Classifier: Programming Language :: Python :: 3.4
Classifier: Programming Language :: Python :: 3.5
Classifier: Programming Language :: Python :: 3.6
Classifier: Programming Language :: Python :: 3.7
Requires-Python: >=3
Requires-Dist: tensorflow
Requires-Dist: numpy
Requires-Dist: pandas
Requires-Dist: matplotlib
Requires-Dist: opencv-python
Requires-Dist: pillow
Requires-Dist: face-recognition
Requires-Dist: transformers
